MyCommonLib/__init__.py
MyCommonLib/configuration.py
MyCommonLib/constants.py
MyCommonLib/customLogger.py
MyCommonLib/dictman.py
MyCommonLib/loginit.py
MyCommonLib/software_mode.py
MyCommonLib/string_manipulator.py
mycommonlib-0.8.6.dist-info/METADATA
mycommonlib-0.8.6.dist-info/WHEEL
mycommonlib-0.8.6.dist-info/RECORD
