Metadata-Version: 2.3
Name: MyCommonLib
Version: 0.8.6
Summary: Common library
License: GPL-3.0-or-later
Keywords: SETUP LIBS
Author: Romolo Politi
Author-email: romolo.politi@inaf.it
Requires-Python: >=3.10,<3.15
Classifier: License :: OSI Approved :: GNU General Public License v3 (GPLv3)
Requires-Dist: pyyaml (>=6.0.2)
Requires-Dist: rich (>=13.9.4)
Requires-Dist: semantic-version-tools (>=1.4.0,<2.0.0)
Requires-Dist: setuptools (>=80.9.0)
Project-URL: Bug Tracker, https://github.com/RomoloPoliti-INAF/myCommonLib/issues
Project-URL: Repository, https://github.com/RomoloPoliti-INAF/myCommonLib
